alice_blue/__init__.py
alice_blue/alice_blue.py
alice_blue-2.0.2.dist-info/LICENSE.txt
alice_blue-2.0.2.dist-info/METADATA
alice_blue-2.0.2.dist-info/WHEEL
alice_blue-2.0.2.dist-info/top_level.txt
alice_blue-2.0.2.dist-info/RECORD
