Metadata-Version: 2.1
Name: alice-blue
Version: 2.0.2
Summary: Official Python library for Alice Blue APIs
Home-page: https://github.com/krishnavelu/alice_blue
Author: Krishna Velu
Author-email: krishnajvelu@gmail.com
License: UNKNOWN
Keywords: alice,alice-blue,python,sdk,trading,stock markets
Platform: UNKNOWN
Classifier: Intended Audience :: Developers
Classifier: Natural Language :: English
Classifier: Operating System :: OS Independent
Classifier: Programming Language :: Python
Classifier: Programming Language :: Python :: 3.6
Classifier: Programming Language :: Python :: Implementation :: PyPy
Classifier: Topic :: Software Development :: Libraries :: Python Modules
Requires-Python: >=3.6
License-File: LICENSE.txt
Requires-Dist: cryptography
Requires-Dist: pytz
Requires-Dist: requests
Requires-Dist: websocket-client
